README.md
setup.py
naivepdf/__init__.py
naivepdf/config.py
naivepdf/exception.py
naivepdf/pdfafm.py
naivepdf/pdfcharset.py
naivepdf/pdfcmap.py
naivepdf/pdfdecryption.py
naivepdf/pdfdocument.py
naivepdf/pdffont.py
naivepdf/pdflexer.py
naivepdf/pdfobject.py
naivepdf/pdfpage.py
naivepdf/pdfparser.py
naivepdf/reconstructor.py
naivepdf.egg-info/PKG-INFO
naivepdf.egg-info/SOURCES.txt
naivepdf.egg-info/dependency_links.txt
naivepdf.egg-info/top_level.txt
naivepdf/Adobe-Core35_AFMs-314/Courier-Bold.afm
naivepdf/Adobe-Core35_AFMs-314/Courier-BoldOblique.afm
naivepdf/Adobe-Core35_AFMs-314/Courier-Oblique.afm
naivepdf/Adobe-Core35_AFMs-314/Courier.afm
naivepdf/Adobe-Core35_AFMs-314/Helvetica-Bold.afm
naivepdf/Adobe-Core35_AFMs-314/Helvetica-BoldOblique.afm
naivepdf/Adobe-Core35_AFMs-314/Helvetica-Narrow.afm
naivepdf/Adobe-Core35_AFMs-314/Helvetica-NarrowBold.afm
naivepdf/Adobe-Core35_AFMs-314/Helvetica-NarrowBoldOblique.afm
naivepdf/Adobe-Core35_AFMs-314/Helvetica-NarrowOblique.afm
naivepdf/Adobe-Core35_AFMs-314/Helvetica-Oblique.afm
naivepdf/Adobe-Core35_AFMs-314/Helvetica.afm
naivepdf/Adobe-Core35_AFMs-314/ITCAvantGarde-Book.afm
naivepdf/Adobe-Core35_AFMs-314/ITCAvantGarde-BookOblique.afm
naivepdf/Adobe-Core35_AFMs-314/ITCAvantGarde-Demi.afm
naivepdf/Adobe-Core35_AFMs-314/ITCAvantGarde-DemiOblique.afm
naivepdf/Adobe-Core35_AFMs-314/ITCBookman-Demi.afm
naivepdf/Adobe-Core35_AFMs-314/ITCBookman-DemiItalic.afm
naivepdf/Adobe-Core35_AFMs-314/ITCBookman-Light.afm
naivepdf/Adobe-Core35_AFMs-314/ITCBookman-LightItalic.afm
naivepdf/Adobe-Core35_AFMs-314/ITCZapfChancery-MediumItalic.afm
naivepdf/Adobe-Core35_AFMs-314/MustRead.html
naivepdf/Adobe-Core35_AFMs-314/NewCenturySchlbk-Bold.afm
naivepdf/Adobe-Core35_AFMs-314/NewCenturySchlbk-BoldItalic.afm
naivepdf/Adobe-Core35_AFMs-314/NewCenturySchlbk-Italic.afm
naivepdf/Adobe-Core35_AFMs-314/NewCenturySchlbk-Roman.afm
naivepdf/Adobe-Core35_AFMs-314/Palatino-Bold.afm
naivepdf/Adobe-Core35_AFMs-314/Palatino-BoldItalic.afm
naivepdf/Adobe-Core35_AFMs-314/Palatino-Italic.afm
naivepdf/Adobe-Core35_AFMs-314/Palatino-Roman.afm
naivepdf/Adobe-Core35_AFMs-314/Symbol.afm
