Metadata-Version: 2.1
Name: naivepdf
Version: 0.3
Summary: yet another pdf texts and tables extractor
Home-page: https://github.com/naivefeeling/naivepdf.git
Author: naivefeeling
Author-email: 625424539@qq.com
License: UNKNOWN
Keywords: pdf,pdfparser,pdfextract
Platform: UNKNOWN
Classifier: Programming Language :: Python :: 3.6
Classifier: Programming Language :: Python :: 3.7
Classifier: License :: OSI Approved :: MIT License
